{
  "top_wind": [
    { "name": "Constanta", "wind_speed": 4.51 },
    { "name": "Bucharest", "wind_speed": 3.6 },
    { "name": "Iasi", "wind_speed": 2.68 },
    { "name": "Cluj-Napoca", "wind_speed": 2.57 },
    { "name": "Timisoara", "wind_speed": 2.57 }
  ],
  "top_solar": [
    { "name": "Constanta", "clouds": 11 },
    { "name": "Brasov", "clouds": 2 },
    { "name": "Bucharest", "clouds": 0 },
    { "name": "Cluj-Napoca", "clouds": 0 },
    { "name": "Iasi", "clouds": 0 }
  ],
  "average_wind": 2.815714285714286,
  "average_solar": 1.8571428571428572
}
